{
  "type": "FeatureCollection",
  "features": {
    "type": "Feature",
    "geometry": {
      "type": "Polygon",
      "coordinates": [
        [
          [
            -73.89,
            78.38
          ],
          [
            -73.5,
            78.56
          ],
          [
            -72.99,
            78.69
          ],
          [
            -70.63,
            78.93
          ],
          [
            -69.26,
            79.19
          ],
          [
            -68.26,
            80.02
          ],
          [
            -68.65,
            80.22
          ],
          [
            -68.42,
            80.36
          ],
          [
            -67.12,
            80.75
          ],
          [
            -66.48,
            80.82
          ],
          [
            -66.4,
            80.83
          ],
          [
            -64.17,
            81.31
          ],
          [
            -62.16,
            81.87
          ],
          [
            -59.63,
            82.3
          ],
          [
            -55.95,
            82.52
          ],
          [
            -51.64,
            82.92
          ],
          [
            -49.83,
            83.01
          ],
          [
            -45.75,
            83.36
          ],
          [
            -40.74,
            83.61
          ],
          [
            -39.22,
            83.74
          ],
          [
            -34.11,
            83.86
          ],
          [
            -30.29,
            83.87
          ],
          [
            -26.39,
            83.73
          ],
          [
            -24.52,
            83.58
          ],
          [
            -23.14,
            83.36
          ],
          [
            -19.06,
            82.83
          ],
          [
            -16.79,
            82.28
          ],
          [
            -11.64,
            81.8
          ],
          [
            -10.62,
            81.62
          ],
          [
            -10.04,
            81.4
          ],
          [
            -10.44,
            81.2
          ],
          [
            -12.05,
            80.92
          ],
          [
            -12.58,
            80.53
          ],
          [
            -14.78,
            80.28
          ],
          [
            -16.83,
            79.64
          ],
          [
            -16.52,
            79.11
          ],
          [
            -16.91,
            78.74
          ],
          [
            -16.51,
            77.77
          ],
          [
            -17.31,
            77.21
          ],
          [
            -17.33,
            76.85
          ],
          [
            -17.88,
            76.48
          ],
          [
            -17.25,
            75.49
          ],
          [
            -16.57,
            75.2
          ],
          [
            -16.58,
            75
          ],
          [
            -17.75,
            74.5
          ],
          [
            -18.71,
            74.17
          ],
          [
            -19.77,
            73.4
          ],
          [
            -20.57,
            73.04
          ],
          [
            -21.34,
            72.26
          ],
          [
            -20.78,
            70.69
          ],
          [
            -20.9,
            70.49
          ],
          [
            -21.58,
            70
          ],
          [
            -21.9,
            69.86
          ],
          [
            -22.84,
            69.52
          ],
          [
            -25.42,
            68.71
          ],
          [
            -26.21,
            68.52
          ],
          [
            -27.45,
            68.31
          ],
          [
            -30.28,
            67.9
          ],
          [
            -32.11,
            67.46
          ],
          [
            -33.4,
            66.63
          ],
          [
            -35.8,
            65.61
          ],
          [
            -36.35,
            65.4
          ],
          [
            -39.34,
            64.85
          ],
          [
            -39.76,
            64.28
          ],
          [
            -40.09,
            63.62
          ],
          [
            -40.81,
            63.01
          ],
          [
            -41.15,
            62.79
          ],
          [
            -41.66,
            61.76
          ],
          [
            -42.67,
            59.95
          ],
          [
            -42.95,
            59.76
          ],
          [
            -43.92,
            59.52
          ],
          [
            -44.11,
            59.52
          ],
          [
            -45.16,
            59.66
          ],
          [
            -47.74,
            60.39
          ],
          [
            -48.74,
            60.59
          ],
          [
            -49.31,
            61.14
          ],
          [
            -49.73,
            61.41
          ],
          [
            -49.99,
            61.66
          ],
          [
            -50.95,
            62.61
          ],
          [
            -51.55,
            63.04
          ],
          [
            -51.78,
            63.31
          ],
          [
            -52.61,
            63.93
          ],
          [
            -52.79,
            64.37
          ],
          [
            -53.71,
            65.44
          ],
          [
            -54.27,
            66.17
          ],
          [
            -54.63,
            66.96
          ],
          [
            -54.5,
            67.81
          ],
          [
            -54.3,
            68.28
          ],
          [
            -54.76,
            69.28
          ],
          [
            -55.29,
            69.49
          ],
          [
            -55.54,
            69.67
          ],
          [
            -55.64,
            70.42
          ],
          [
            -56.11,
            71.41
          ],
          [
            -56.47,
            71.63
          ],
          [
            -56.68,
            72.1
          ],
          [
            -57.58,
            72.98
          ],
          [
            -58.54,
            73.97
          ],
          [
            -58.7,
            74.6
          ],
          [
            -60.73,
            75.33
          ],
          [
            -65.13,
            75.75
          ],
          [
            -66.61,
            75.71
          ],
          [
            -68.97,
            75.89
          ],
          [
            -70.83,
            76.29
          ],
          [
            -71.64,
            76.68
          ],
          [
            -71.88,
            76.57
          ],
          [
            -72.3,
            76.51
          ],
          [
            -73.09,
            76.48
          ],
          [
            -73.63,
            76.53
          ],
          [
            -74.12,
            76.71
          ],
          [
            -73.87,
            76.89
          ],
          [
            -73.13,
            76.95
          ],
          [
            -72.08,
            76.89
          ],
          [
            -73.65,
            77.39
          ],
          [
            -74,
            78.16
          ],
          [
            -73.89,
            78.38
          ]
        ]
      ]
    },
    "properties": {
      "A3": "GRL"
    }
  }
}