{
  "type": "FeatureCollection",
  "features": [
    {
      "type": "Feature",
      "properties": {
        "type": "marina",
        "channel": 31,
        "name": "Jachtclub Scheveningen",
        "url": "https://www.jachtclubscheveningen.com/",
        "phone": "+31653293137",
        "vhfdata": {
          "generic": {
            "mode": "listen",
            "note": "Guests dock inguest berth, bow facing north. In the harbour office there is a sign post. Red on top of white: no entering. White on top of red: no exit."
          }
        }
      },
      "geometry": {
        "type": "Polygon",
        "coordinates": [
          [
            [
              4.266825031143,
              52.097200321544
            ],
            [
              4.264432960605,
              52.095554858692
            ],
            [
              4.264272927717,
              52.095679046685
            ],
            [
              4.263177965852,
              52.09482524725
            ],
            [
              4.264146585964,
              52.094261213206
            ],
            [
              4.267608350016,
              52.09664149191
            ],
            [
              4.266825031143,
              52.097200321544
            ]
          ]
        ]
      }
    },
    {
      "type": "Feature",
      "properties": {
        "name": "Verkeerscentrale Scheveningen",
        "type": "vts",
        "channel": 21,
        "url": "https://varendoejesamen.nl/kenniscentrum/artikel/knooppunt-6-6",
        "phone": "+31703527721",
        "vhfdata": {
          "generic": {
            "mode": "report",
            "note": "Request entrance. In the 'voorhaven' there is a sign post. Red on top of white: no entering. White on top of red: no exit."
          }
        }
      },
      "geometry": {
        "type": "Polygon",
        "coordinates": [
          [
            [
              4.260364766111,
              52.098808454926
            ],
            [
              4.260505309252,
              52.098719014166
            ],
            [
              4.260736423013,
              52.098192982435
            ],
            [
              4.259067115825,
              52.097868650488
            ],
            [
              4.259418068239,
              52.097013097135
            ],
            [
              4.26107199068,
              52.097305628155
            ],
            [
              4.261422157561,
              52.097084534549
            ],
            [
              4.262089137132,
              52.096739392083
            ],
            [
              4.262864665969,
              52.096945442973
            ],
            [
              4.263571948092,
              52.09679040573
            ],
            [
              4.264550228264,
              52.097393765016
            ],
            [
              4.264539488414,
              52.097644045884
            ],
            [
              4.264222662893,
              52.097723217952
            ],
            [
              4.263589011855,
              52.098175155818
            ],
            [
              4.263562162235,
              52.098277418495
            ],
            [
              4.26407230502,
              52.098607296502
            ],
            [
              4.264303211755,
              52.098607296502
            ],
            [
              4.26478650492,
              52.098346693079
            ],
            [
              4.264969485093,
              52.098396174858
            ],
            [
              4.266759173442,
              52.097434173214
            ],
            [
              4.266822643951,
              52.097241068322
            ],
            [
              4.267613175353,
              52.096675386585
            ],
            [
              4.271680816402,
              52.099564291821
            ],
            [
              4.270823257401,
              52.100079627815
            ],
            [
              4.267337093638,
              52.097583055777
            ],
            [
              4.266982884485,
              52.09757160329
            ],
            [
              4.26541690718,
              52.098361818014
            ],
            [
              4.265342336832,
              52.098716837463
            ],
            [
              4.26873528766,
              52.101053024004
            ],
            [
              4.267187952942,
              52.101877531216
            ],
            [
              4.263235511028,
              52.099146467476
            ],
            [
              4.261249221755,
              52.099195160691
            ],
            [
              4.261051055233,
              52.09930806403
            ],
            [
              4.260364766111,
              52.098808454926
            ]
          ]
        ]
      }
    },
    {
      "type": "Feature",
      "properties": {
        "name": "Naviduct Krabbersgat",
        "callname": "Naviduct",
        "type": "lock",
        "channel": 22,
        "url": "https://waterkaart.net/gids/sluis.php?naam=Naviduct-Krabbersgat",
        "phone": "+31887973915",
        "vhfdata": {
          "generic": {
            "mode": "report"
          }
        }
      },
      "geometry": {
        "type": "Polygon",
        "coordinates": [
          [
            [
              5.295409326493,
              52.691437386264
            ],
            [
              5.294996714883,
              52.690190359817
            ],
            [
              5.295477153058,
              52.690173230084
            ],
            [
              5.295827590316,
              52.691399701921
            ],
            [
              5.295409326493,
              52.691437386264
            ]
          ]
        ]
      }
    },
    {
      "type": "Feature",
      "properties": {
        "name": "Stevinsluis",
        "type": "lock",
        "channel": 20,
        "url": "https://waterkaart.net/gids/sluis.php?naam=Stevinsluis",
        "phone": "+31887974540",
        "vhfdata": {
          "generic": {
            "mode": "report"
          }
        }
      },
      "geometry": {
        "type": "Polygon",
        "coordinates": [
          [
            [
              5.047716383113,
              52.930226130953
            ],
            [
              5.046274389478,
              52.931364184914
            ],
            [
              5.046076246589,
              52.931274608688
            ],
            [
              5.047531903857,
              52.930148907465
            ],
            [
              5.047716383113,
              52.930226130953
            ]
          ]
        ]
      }
    },
    {
      "type": "Feature",
      "properties": {
        "name": "Gemeentehaven Oudeschild",
        "callname": "Oudeschild",
        "type": "marina",
        "channel": 12,
        "url": "https://www.havenoudeschild.nl/",
        "phone": "+31222312710",
        "vhfdata": {
          "generic": {
            "mode": "report",
            "note": "Listen when approaching. On Mon and Fri announce due to fishing boats."
          }
        }
      },
      "geometry": {
        "type": "Polygon",
        "coordinates": [
          [
            [
              4.85312135871,
              53.038865610783
            ],
            [
              4.853369343932,
              53.039253286861
            ],
            [
              4.85225341043,
              53.039566407276
            ],
            [
              4.85279897792,
              53.040356653423
            ],
            [
              4.856097181381,
              53.041340713528
            ],
            [
              4.858552235086,
              53.04329385684
            ],
            [
              4.858800220308,
              53.044054217076
            ],
            [
              4.859717765632,
              53.04436730265
            ],
            [
              4.860312930166,
              53.046409757487
            ],
            [
              4.860635310956,
              53.046782457782
            ],
            [
              4.860015347899,
              53.04702098428
            ],
            [
              4.856593151827,
              53.044680385949
            ],
            [
              4.853294948366,
              53.043383311762
            ],
            [
              4.851385462151,
              53.040177731135
            ],
            [
              4.850864693183,
              53.03990934613
            ],
            [
              4.850343924216,
              53.040356653544
            ],
            [
              4.84962476707,
              53.040147910662
            ],
            [
              4.849128796625,
              53.039029628011
            ],
            [
              4.850319125693,
              53.038835789402
            ],
            [
              4.851385462151,
              53.039312929025
            ],
            [
              4.85312135871,
              53.038865610783
            ]
          ]
        ]
      }
    },
    {
      "type": "Feature",
      "properties": {
        "name": "Hoek van Holland",
        "callname": "Sector Maasmond",
        "type": "vts",
        "channel": 3,
        "url": "https://www.portofrotterdam.com/sites/default/files/2022-07/procedure-VHF-communication-VTS-HCC-2022-English.pdf",
        "phone": "+31102522801",
        "vhfdata": {
          "generic": {
            "mode": "report"
          },
          "pleasure": {
            "mode": "report",
            "note": "Report using the corridor."
          }
        }
      },
      "geometry": {
        "type": "Polygon",
        "coordinates": [
          [
            [
              4.101444217083,
              51.982955781815
            ],
            [
              4.046939440956,
              51.994410135022
            ],
            [
              4.031111111111,
              52.0366667
            ],
            [
              4.001388888889,
              52.1197222
            ],
            [
              3.968995736407,
              52.014758795614
            ],
            [
              3.882495441597,
              51.964054476943
            ],
            [
              3.964444444444,
              51.9686111
            ],
            [
              3.981698862183,
              51.983782142355
            ],
            [
              4.004781812857,
              51.988696063156
            ],
            [
              4.021816470081,
              51.985099376325
            ],
            [
              4.029862858152,
              51.987209340383
            ],
            [
              4.034141347889,
              51.98741924141
            ],
            [
              4.037909246223,
              51.986764429324
            ],
            [
              4.041742275664,
              51.985775863238
            ],
            [
              4.04085867659,
              51.983908192065
            ],
            [
              4.057293167902,
              51.981106432937
            ],
            [
              4.07284406014,
              51.976437002636
            ],
            [
              4.08076606839,
              51.981611706259
            ],
            [
              4.097502998083,
              51.977558438839
            ],
            [
              4.101444217083,
              51.982955781815
            ]
          ]
        ]
      }
    },
    {
      "type": "Feature",
      "properties": {
        "name": "Hoek van Holland",
        "callname": "Sector Pilot Maas",
        "type": "vts",
        "channel": 2,
        "url": "https://www.portofrotterdam.com/sites/default/files/2022-07/procedure-VHF-communication-VTS-HCC-2022-English.pdf",
        "phone": "+31102522801",
        "vhfdata": {
          "generic": {
            "mode": "report"
          }
        }
      },
      "geometry": {
        "type": "Polygon",
        "coordinates": [
          [
            [
              3.968995861755,
              52.014758872636
            ],
            [
              4.001388888889,
              52.1197222
            ],
            [
              3.6375,
              52.1180556
            ],
            [
              3.577777777778,
              52.0838889
            ],
            [
              3.594444444444,
              51.9377778
            ],
            [
              3.6675,
              51.9519444
            ],
            [
              3.882495441597,
              51.964054476943
            ],
            [
              3.968995861755,
              52.014758872636
            ]
          ]
        ]
      }
    },
    {
      "type": "Feature",
      "properties": {
        "name": "Hoek van Holland",
        "callname": "Sector Maasmond",
        "type": "vts",
        "channel": 3,
        "url": "https://www.portofrotterdam.com/sites/default/files/2021-05/aanbevolen-oversteekroute-voor-kleine-vaartuigen-haven-rotterdam.pdf",
        "phone": "+31102522801",
        "vhfdata": {
          "generic": {
            "mode": "report"
          },
          "pleasure": {
            "mode": "report",
            "note": "Report upon entering ship name, direction and current position relative to buoy MV or MN1"
          },
          "passenger": {
            "mode": "report",
            "note": "Report upon entering ship name, direction and current position relative to buoy MV or MN1"
          }
        }
      },
      "geometry": {
        "type": "Polygon",
        "coordinates": [
          [
            [
              4.031548217773,
              52.036774474766
            ],
            [
              4.043221191406,
              52.031705461665
            ],
            [
              3.945202545166,
              51.973581992163
            ],
            [
              3.930096343994,
              51.97855185636
            ],
            [
              4.031548217773,
              52.036774474766
            ]
          ]
        ]
      }
    },
    {
      "type": "Feature",
      "properties": {
        "name": "Hoek van Holland",
        "callname": "Sector Rozenburg",
        "type": "vts",
        "channel": 65,
        "url": "https://www.binnenvaartkennis.nl/wp-content/uploads/2021/01/Rotterdam.pdf",
        "phone": "+31102522801",
        "vhfdata": {
          "generic": {
            "mode": "report"
          },
          "pleasure": {
            "mode": "listen"
          }
        }
      },
      "geometry": {
        "type": "Polygon",
        "coordinates": [
          [
            [
              4.097504262048,
              51.977555663421
            ],
            [
              4.101452496488,
              51.982954031537
            ],
            [
              4.121415004453,
              51.97726601936
            ],
            [
              4.145950538927,
              51.967307271322
            ],
            [
              4.139674683174,
              51.963131824559
            ],
            [
              4.123989285592,
              51.971290268957
            ],
            [
              4.123021661722,
              51.970866716173
            ],
            [
              4.126204498999,
              51.967862625732
            ],
            [
              4.218974802198,
              51.922624352389
            ],
            [
              4.219208038715,
              51.919811325309
            ],
            [
              4.222523092914,
              51.916326443762
            ],
            [
              4.224924308274,
              51.912876744319
            ],
            [
              4.229214281719,
              51.899766718775
            ],
            [
              4.23240781143,
              51.897513268241
            ],
            [
              4.251288900793,
              51.893992949963
            ],
            [
              4.250434744172,
              51.89215607938
            ],
            [
              4.236456356393,
              51.894712973789
            ],
            [
              4.231451894082,
              51.89398407367
            ],
            [
              4.23175698199,
              51.892728936548
            ],
            [
              4.23001608327,
              51.89257861209
            ],
            [
              4.229304892723,
              51.894592774905
            ],
            [
              4.227157891363,
              51.894384939938
            ],
            [
              4.224738357357,
              51.902338442974
            ],
            [
              4.222586758171,
              51.910352310785
            ],
            [
              4.221377555287,
              51.91276383989
            ],
            [
              4.21841426012,
              51.915576964503
            ],
            [
              4.216107786618,
              51.914602814157
            ],
            [
              4.207825173848,
              51.914581115632
            ],
            [
              4.207195961367,
              51.914982182248
            ],
            [
              4.202533012131,
              51.914911121266
            ],
            [
              4.201742682622,
              51.915344531184
            ],
            [
              4.201645363247,
              51.919267668891
            ],
            [
              4.196946158609,
              51.919278587932
            ],
            [
              4.196922201648,
              51.92728232055
            ],
            [
              4.190141510323,
              51.930731622316
            ],
            [
              4.189961397112,
              51.931491281189
            ],
            [
              4.188404966005,
              51.932196188947
            ],
            [
              4.184539872619,
              51.932196189322
            ],
            [
              4.184504050798,
              51.933099563529
            ],
            [
              4.186626032567,
              51.933154284954
            ],
            [
              4.172293783463,
              51.940125603681
            ],
            [
              4.172153431393,
              51.937542211686
            ],
            [
              4.168598176469,
              51.937497341364
            ],
            [
              4.168620938862,
              51.938120889452
            ],
            [
              4.166766846397,
              51.938103533174
            ],
            [
              4.165744883219,
              51.938608026883
            ],
            [
              4.165690263051,
              51.939379859361
            ],
            [
              4.164346826461,
              51.939422325199
            ],
            [
              4.164328485718,
              51.938931452476
            ],
            [
              4.159159427083,
              51.938915109036
            ],
            [
              4.159117179793,
              51.943767502013
            ],
            [
              4.156790523001,
              51.947916389958
            ],
            [
              4.149706310378,
              51.951290005768
            ],
            [
              4.149480951163,
              51.948207039839
            ],
            [
              4.142978737228,
              51.951278916293
            ],
            [
              4.137231153952,
              51.951539829859
            ],
            [
              4.137047146449,
              51.956812182535
            ],
            [
              4.133540704085,
              51.958125568793
            ],
            [
              4.133565489361,
              51.954851306489
            ],
            [
              4.132572095246,
              51.954192471944
            ],
            [
              4.132573787028,
              51.951202037842
            ],
            [
              4.131228866872,
              51.950422104688
            ],
            [
              4.131654930218,
              51.943070492039
            ],
            [
              4.127149085567,
              51.943021926137
            ],
            [
              4.127144569018,
              51.946214454351
            ],
            [
              4.127641956474,
              51.946664346506
            ],
            [
              4.127528665815,
              51.948209266451
            ],
            [
              4.123905049871,
              51.948177471876
            ],
            [
              4.124053598548,
              51.950808779941
            ],
            [
              4.125025134672,
              51.952108576726
            ],
            [
              4.125559458715,
              51.955881021755
            ],
            [
              4.123830567284,
              51.957117525557
            ],
            [
              4.122658567135,
              51.960772861908
            ],
            [
              4.120838085892,
              51.961443610104
            ],
            [
              4.121692313846,
              51.962906725499
            ],
            [
              4.106321358039,
              51.967143507246
            ],
            [
              4.105492884213,
              51.968308277899
            ],
            [
              4.104688144733,
              51.968541834679
            ],
            [
              4.108763629856,
              51.974199025793
            ],
            [
              4.097504262048,
              51.977555663421
            ]
          ]
        ]
      }
    },
    {
      "type": "Feature",
      "properties": {
        "name": "Rotterdam",
        "callname": "Sector Maassluis",
        "type": "vts",
        "channel": 80,
        "url": "https://www.binnenvaartkennis.nl/wp-content/uploads/2021/01/Rotterdam.pdf",
        "phone": "+31102522601",
        "vhfdata": {
          "generic": {
            "mode": "report"
          },
          "pleasure": {
            "mode": "listen"
          }
        }
      },
      "geometry": {
        "type": "Polygon",
        "coordinates": [
          [
            [
              4.145951022644,
              51.967307078491
            ],
            [
              4.13967488628,
              51.963131807201
            ],
            [
              4.157087597467,
              51.954321677107
            ],
            [
              4.159695229679,
              51.954368431083
            ],
            [
              4.163976407455,
              51.952239233957
            ],
            [
              4.164249090607,
              51.950846850636
            ],
            [
              4.176468318446,
              51.944681275997
            ],
            [
              4.184265719576,
              51.940752589783
            ],
            [
              4.197888931393,
              51.935835759889
            ],
            [
              4.209399629179,
              51.93190723215
            ],
            [
              4.21743301424,
              51.928540778945
            ],
            [
              4.22287941478,
              51.9251638129
            ],
            [
              4.226116317248,
              51.919893355124
            ],
            [
              4.229850494189,
              51.916635161756
            ],
            [
              4.235852864725,
              51.913404283738
            ],
            [
              4.237748102463,
              51.913716681613
            ],
            [
              4.243318887467,
              51.912133718866
            ],
            [
              4.243019316068,
              51.910937970021
            ],
            [
              4.245138770772,
              51.910783070079
            ],
            [
              4.253504412972,
              51.908133208947
            ],
            [
              4.261257197706,
              51.905087256231
            ],
            [
              4.265182386196,
              51.90898545354
            ],
            [
              4.254496815116,
              51.913250663069
            ],
            [
              4.245702141586,
              51.915718029921
            ],
            [
              4.24311951145,
              51.916898182441
            ],
            [
              4.238393138648,
              51.91936786869
            ],
            [
              4.227807724533,
              51.92913964953
            ],
            [
              4.221523455937,
              51.932942566155
            ],
            [
              4.212682364317,
              51.936824076164
            ],
            [
              4.199486659341,
              51.941410960376
            ],
            [
              4.188054626082,
              51.945797583065
            ],
            [
              4.175097694705,
              51.952072197494
            ],
            [
              4.172741650684,
              51.953216798098
            ],
            [
              4.172737877267,
              51.953266730026
            ],
            [
              4.172773261048,
              51.953289042111
            ],
            [
              4.172877449413,
              51.953310162396
            ],
            [
              4.17352836242,
              51.953805900642
            ],
            [
              4.172840650269,
              51.954191457703
            ],
            [
              4.172374694381,
              51.954144077763
            ],
            [
              4.172454290846,
              51.953533128101
            ],
            [
              4.172554315946,
              51.953474422801
            ],
            [
              4.172553497511,
              51.953404313867
            ],
            [
              4.172513302258,
              51.953371785055
            ],
            [
              4.172422222092,
              51.953370540111
            ],
            [
              4.169769829145,
              51.954823316502
            ],
            [
              4.167574383458,
              51.954716855329
            ],
            [
              4.163217079964,
              51.956885535854
            ],
            [
              4.162947035957,
              51.958409283846
            ],
            [
              4.145951022644,
              51.967307078491
            ]
          ]
        ]
      }
    },
    {
      "type": "Feature",
      "properties": {
        "name": "Waddenhaven Vlieland",
        "type": "marina",
        "channel": 12,
        "url": "http://www.waddenhavenvlieland.nl/",
        "phone": "+31562451729",
        "vhfdata": {
          "generic": {
            "mode": "Listen"
          },
          "passenger": {
            "mode": "announce"
          }
        }
      },
      "geometry": {
        "type": "Polygon",
        "coordinates": [
          [
            [
              5.091797534605,
              53.294655313524
            ],
            [
              5.091141117466,
              53.295263208128
            ],
            [
              5.091959495425,
              53.295660053684
            ],
            [
              5.090847736687,
              53.296439890605
            ],
            [
              5.091110235279,
              53.296606007873
            ],
            [
              5.0886551014,
              53.297888780574
            ],
            [
              5.087080109856,
              53.297962608046
            ],
            [
              5.086230849709,
              53.297275084772
            ],
            [
              5.086230849709,
              53.296790581857
            ],
            [
              5.088099222032,
              53.296633694021
            ],
            [
              5.089010246553,
              53.296292230269
            ],
            [
              5.091499050823,
              53.294625986872
            ],
            [
              5.091797534605,
              53.294655313524
            ]
          ]
        ]
      }
    },
    {
      "type": "Feature",
      "properties": {
        "name": "Passantenhaven Terschelling",
        "callname": "Terschelling",
        "type": "marina",
        "channel": 31,
        "url": "https://www.jachthaventerschelling.nl/",
        "phone": "+31562443337",
        "vhfdata": {
          "generic": {
            "mode": "Listen"
          },
          "passenger": {
            "mode": "announce"
          }
        }
      },
      "geometry": {
        "type": "Polygon",
        "coordinates": [
          [
            [
              5.222461336366,
              53.36387588411
            ],
            [
              5.223905566457,
              53.364216481009
            ],
            [
              5.225349796546,
              53.364345494251
            ],
            [
              5.225963810535,
              53.364448704574
            ],
            [
              5.226223253066,
              53.364763494519
            ],
            [
              5.226119476054,
              53.365811057424
            ],
            [
              5.224190953239,
              53.365754293583
            ],
            [
              5.220800904167,
              53.365171169809
            ],
            [
              5.221198716047,
              53.36431453112
            ],
            [
              5.222158653414,
              53.36430421005
            ],
            [
              5.222461336366,
              53.36387588411
            ]
          ]
        ]
      }
    },
    {
      "type": "Feature",
      "properties": {
        "name": "Waddenhaven Ameland",
        "callname": "Ameland",
        "type": "marina",
        "channel": 31,
        "url": "https://waddenhavenameland.nl/",
        "phone": "+31519542159",
        "vhfdata": {
          "generic": {
            "mode": "Listen"
          }
        }
      },
      "geometry": {
        "type": "Polygon",
        "coordinates": [
          [
            [
              5.775892678261,
              53.436550531309
            ],
            [
              5.775860821609,
              53.437138826946
            ],
            [
              5.776041342642,
              53.437252689677
            ],
            [
              5.776030723757,
              53.437948510847
            ],
            [
              5.774915740907,
              53.437942185251
            ],
            [
              5.775021929751,
              53.436544205505
            ],
            [
              5.775892678261,
              53.436550531309
            ]
          ]
        ]
      }
    },
    {
      "type": "Feature",
      "properties": {
        "name": "Waddenhaven Texel",
        "type": "marina",
        "channel": 31,
        "url": "https://www.waddenhaventexel.nl/",
        "phone": "+31222321227",
        "vhfdata": {
          "generic": {
            "mode": "Listen"
          }
        }
      },
      "geometry": {
        "type": "Polygon",
        "coordinates": [
          [
            [
              4.858450721849,
              53.043988051107
            ],
            [
              4.859727590248,
              53.044616870672
            ],
            [
              4.86039319186,
              53.04656043675
            ],
            [
              4.86054261263,
              53.046731923709
            ],
            [
              4.859972096962,
              53.047034065652
            ],
            [
              4.856549002955,
              53.044682202022
            ],
            [
              4.856847844495,
              53.044224880325
            ],
            [
              4.857798703942,
              53.04430654528
            ],
            [
              4.857975292125,
              53.044102382619
            ],
            [
              4.858450721849,
              53.043988051107
            ]
          ]
        ]
      }
    },
    {
      "type": "Feature",
      "properties": {
        "name": "Den Helder",
        "type": "vts",
        "channel": 62,
        "url": "https://www.binnenvaartkennis.nl/wp-content/uploads/2021/03/VTS-Procedures-Den-Helder.pdf",
        "phone": "+31223657522",
        "update": "5 *",
        "vhfdata": {
          "generic": {
            "mode": "report",
            "note": "Report 2h before entering, when entering, anchoring, passing Moermanbrug and 1h before leaving."
          },
          "pleasure": {
            "url": "https://varendoejesamen.nl/kenniscentrum/artikel/knooppunt-6-8"
          }
        }
      },
      "geometry": {
        "type": "Polygon",
        "coordinates": [
          [
            [
              4.708151535034,
              52.881124394525
            ],
            [
              4.631719306946,
              52.881720047961
            ],
            [
              4.57850428009,
              52.910793522242
            ],
            [
              4.563398078919,
              52.946183482942
            ],
            [
              4.589404777527,
              53.003772512323
            ],
            [
              4.626703576088,
              53.065220902829
            ],
            [
              4.723177269935,
              53.065014597793
            ],
            [
              4.82741864109,
              53.017847984102
            ],
            [
              4.843125657081,
              53.012297096534
            ],
            [
              4.875119046211,
              52.99481359075
            ],
            [
              4.877307728767,
              52.989595574878
            ],
            [
              4.830937699318,
              52.973162456786
            ],
            [
              4.80291397953,
              52.964400740943
            ],
            [
              4.784760788917,
              52.963082453004
            ],
            [
              4.779610947609,
              52.965240805423
            ],
            [
              4.762444809913,
              52.965499283516
            ],
            [
              4.755406693458,
              52.964000089056
            ],
            [
              4.730687455177,
              52.962655939477
            ],
            [
              4.716267899513,
              52.94610913745
            ],
            [
              4.708151535034,
              52.881124394525
            ]
          ]
        ]
      }
    },
    {
      "type": "Feature",
      "properties": {
        "name": "Terschelling",
        "type": "vts",
        "channel": 2,
        "phone": "+31887974599",
        "vhfdata": {
          "generic": {
            "mode": "listen"
          },
          "passenger": {
            "mode": "report",
            "note": "Report number of head onboard and destination"
          }
        }
      },
      "geometry": {
        "type": "Polygon",
        "coordinates": [
          [
            [
              5.23533333,
              53.3583333
            ],
            [
              5.23533333,
              53.3228333
            ],
            [
              5.28,
              53.3228333
            ],
            [
              5.28,
              53.2961667
            ],
            [
              5.19275,
              53.24525
            ],
            [
              5.14366666,
              53.24525
            ],
            [
              5.0755,
              53.2955833
            ],
            [
              4.983666666,
              53.28925
            ],
            [
              4.931666666,
              53.3298333
            ],
            [
              5.03865,
              53.4025833
            ],
            [
              5.03865,
              53.43675
            ],
            [
              5.16115,
              53.43675
            ],
            [
              5.19253333,
              53.3926333
            ],
            [
              5.23533333,
              53.3583333
            ]
          ]
        ]
      }
    },
    {
      "type": "Feature",
      "properties": {
        "name": "Centrale meldpost Waddenzee",
        "type": "vts",
        "channel": 4,
        "phone": "+31887974599",
        "vhfdata": {
          "generic": {
            "mode": "listen",
            "note": "Ship to ship on VHF 10"
          },
          "cargo": {
            "mode": "report",
            "note": "Ships with dangerous cargo and special transports have a reporting obligation"
          }
        }
      },
      "geometry": {
        "type": "Polygon",
        "coordinates": [
          [
            [
              6.799066690907,
              53.456245942282
            ],
            [
              6.640017993285,
              53.55304528546
            ],
            [
              6.112795711163,
              53.470458155585
            ],
            [
              5.960093075967,
              53.462966459337
            ],
            [
              5.608201877275,
              53.442920565456
            ],
            [
              5.535983185234,
              53.437904620402
            ],
            [
              5.221637911515,
              53.369315358986
            ],
            [
              5.235333851308,
              53.358333198139
            ],
            [
              5.235335153133,
              53.322834642745
            ],
            [
              5.280019974636,
              53.322841877764
            ],
            [
              5.280036072355,
              53.296159368817
            ],
            [
              5.192808217607,
              53.245232971464
            ],
            [
              5.143681484876,
              53.245223695085
            ],
            [
              5.075500394269,
              53.295574407913
            ],
            [
              5.053640108341,
              53.294026712411
            ],
            [
              5.012020282427,
              53.287123779097
            ],
            [
              4.873179058956,
              53.207912281439
            ],
            [
              4.860751997583,
              53.185987551838
            ],
            [
              4.77646489188,
              53.040919024039
            ],
            [
              4.827379766828,
              53.017884729378
            ],
            [
              4.843125165003,
              53.012300598458
            ],
            [
              4.875121429674,
              52.994813276914
            ],
            [
              4.8773199523,
              52.989594161285
            ],
            [
              4.83077805774,
              52.973140609212
            ],
            [
              4.802915184967,
              52.964395060473
            ],
            [
              4.784765230093,
              52.963078091667
            ],
            [
              4.779607792352,
              52.965239648711
            ],
            [
              4.762451428675,
              52.965470785019
            ],
            [
              4.80075560363,
              52.908963275321
            ],
            [
              4.868048492208,
              52.884882186262
            ],
            [
              4.931224646664,
              52.897996484022
            ],
            [
              5.038457223618,
              52.937640737703
            ],
            [
              5.295138417429,
              53.067390395972
            ],
            [
              5.348167494207,
              53.078902558673
            ],
            [
              5.382205664072,
              53.0974001743
            ],
            [
              5.411281585693,
              53.125452970005
            ],
            [
              5.416259765625,
              53.165607305587
            ],
            [
              5.401067733765,
              53.175099860501
            ],
            [
              5.412826538086,
              53.182687248963
            ],
            [
              5.421237945557,
              53.185156075783
            ],
            [
              5.430679321289,
              53.199554733239
            ],
            [
              5.48599027521,
              53.244099253767
            ],
            [
              5.53673786188,
              53.261043562185
            ],
            [
              5.58287467238,
              53.302525551097
            ],
            [
              5.732482081076,
              53.33828318048
            ],
            [
              5.872008798379,
              53.383161497944
            ],
            [
              5.99515648434,
              53.398243007428
            ],
            [
              6.079358400678,
              53.403283859971
            ],
            [
              6.138791417001,
              53.404371827179
            ],
            [
              6.178068525388,
              53.415461128891
            ],
            [
              6.201946603606,
              53.407871996272
            ],
            [
              6.250688337703,
              53.415903883733
            ],
            [
              6.306010000543,
              53.396136986839
            ],
            [
              6.37112915845,
              53.415489837976
            ],
            [
              6.513891658612,
              53.426623432505
            ],
            [
              6.609293240544,
              53.439833193875
            ],
            [
              6.691053369043,
              53.462317171599
            ],
            [
              6.799066690907,
              53.456245942282
            ]
          ]
        ]
      }
    },
    {
      "type": "Feature",
      "properties": {
        "name": "Prinses Margrietsluis ",
        "type": "lock",
        "channel": 20,
        "url": "https://waterkaart.net/gids/sluis.php?naam=Prinses%20Margrietsluis",
        "phone": "+31887975555",
        "vhfdata": {
          "generic": {
            "mode": "report"
          },
          "pleasure": {
            "mode": "listen"
          }
        }
      },
      "geometry": {
        "type": "Polygon",
        "coordinates": [
          [
            [
              5.676861355006,
              52.852785308119
            ],
            [
              5.675364315838,
              52.850212256045
            ],
            [
              5.675986652374,
              52.850070761549
            ],
            [
              5.677497350763,
              52.852679291006
            ],
            [
              5.676861355006,
              52.852785308119
            ]
          ]
        ]
      }
    },
    {
      "type": "Feature",
      "properties": {
        "name": "Lemstersluis",
        "type": "lock",
        "channel": 22,
        "vhfdata": {
          "generic": {
            "mode": "report"
          },
          "pleasure": {
            "mode": "listen"
          }
        }
      },
      "geometry": {
        "type": "Polygon",
        "coordinates": [
          [
            [
              5.712688364674,
              52.838246014853
            ],
            [
              5.712428524007,
              52.837917822175
            ],
            [
              5.715776925331,
              52.837058088294
            ],
            [
              5.716095820695,
              52.837511145199
            ],
            [
              5.712688364674,
              52.838246014853
            ]
          ]
        ]
      }
    },
    {
      "type": "Feature",
      "properties": {
        "name": "Houtribsluis",
        "type": "lock",
        "channel": 20,
        "url": "https://waterkaart.net/gids/sluis.php?naam=Houtribsluizen",
        "phone": "+31887973302",
        "vhfdata": {
          "generic": {
            "mode": "report"
          },
          "pleasure": {
            "mode": "listen"
          }
        }
      },
      "geometry": {
        "type": "Polygon",
        "coordinates": [
          [
            [
              5.433928437502,
              52.528627334164
            ],
            [
              5.433806711425,
              52.526562527423
            ],
            [
              5.434717654326,
              52.526527380865
            ],
            [
              5.435010484623,
              52.528586427902
            ],
            [
              5.433928437502,
              52.528627334164
            ]
          ]
        ]
      }
    },
    {
      "type": "Feature",
      "properties": {
        "name": "Oranjesluizen",
        "type": "lock",
        "channel": 18,
        "url": "https://waterkaart.net/gids/sluis.php?naam=Oranjesluizen",
        "phone": "+31887973464",
        "vhfdata": {
          "generic": {
            "mode": "report"
          },
          "pleasure": {
            "mode": "listen"
          }
        }
      },
      "geometry": {
        "type": "Polygon",
        "coordinates": [
          [
            [
              4.958662228315,
              52.380165517648
            ],
            [
              4.961472266013,
              52.37940569281
            ],
            [
              4.961641826915,
              52.379657370636
            ],
            [
              4.960783892299,
              52.381222216799
            ],
            [
              4.960952057663,
              52.381355126558
            ],
            [
              4.961126757527,
              52.381300568265
            ],
            [
              4.961325863747,
              52.38147265379
            ],
            [
              4.961181712655,
              52.381547589353
            ],
            [
              4.9613508255,
              52.381677517433
            ],
            [
              4.960265313101,
              52.382195266288
            ],
            [
              4.959850413308,
              52.381833223858
            ],
            [
              4.960004015049,
              52.381760357084
            ],
            [
              4.959873366023,
              52.381646611326
            ],
            [
              4.960236443511,
              52.381449968559
            ],
            [
              4.958826098344,
              52.380398281341
            ],
            [
              4.958662228315,
              52.380165517648
            ]
          ]
        ]
      }
    },
    {
      "type": "Feature",
      "properties": {
        "name": "Sector Schellingwoude",
        "callname": "Schellingwoude",
        "type": "vts",
        "channel": 60,
        "url": "https://www.binnenvaartkennis.nl/wp-content/uploads/2021/02/VTS-Amsterdam.pdf",
        "phone": "+31206221515",
        "vhfdata": {
          "generic": {
            "mode": "listen"
          },
          "cargo": {
            "mode": "report",
            "note": "Report destination."
          }
        }
      },
      "geometry": {
        "type": "Polygon",
        "coordinates": [
          [
            [
              4.979819232684,
              52.374961465744
            ],
            [
              4.973434325538,
              52.379861173598
            ],
            [
              4.969271438663,
              52.37977041913
            ],
            [
              4.95960759413,
              52.384670893428
            ],
            [
              4.932994853035,
              52.383581946144
            ],
            [
              4.93596834366,
              52.365610437935
            ],
            [
              4.971055533037,
              52.354987472707
            ],
            [
              5.008521514915,
              52.335369134523
            ],
            [
              5.010156934758,
              52.336640957323
            ],
            [
              4.958566872411,
              52.365792004883
            ],
            [
              4.955277708626,
              52.377950091938
            ],
            [
              4.958126724488,
              52.380062367127
            ],
            [
              4.982108695588,
              52.368100796229
            ],
            [
              4.989194973327,
              52.366821112635
            ],
            [
              4.998535344828,
              52.366494552274
            ],
            [
              5.015910092157,
              52.368074291136
            ],
            [
              5.014882663128,
              52.372264777611
            ],
            [
              4.998223339637,
              52.379713496258
            ],
            [
              4.979819232684,
              52.374961465744
            ]
          ]
        ]
      }
    },
    {
      "type": "Feature",
      "properties": {
        "name": "Amsterdam Port Control",
        "type": "vts",
        "channel": 4,
        "url": "https://www.binnenvaartkennis.nl/wp-content/uploads/2021/02/VTS-Amsterdam.pdf",
        "phone": "+31206221515",
        "vhfdata": {
          "generic": {
            "mode": "listen"
          },
          "cargo": {
            "mode": "report",
            "note": "Report destination."
          }
        }
      },
      "geometry": {
        "type": "Polygon",
        "coordinates": [
          [
            [
              4.792837224524,
              52.425351656925
            ],
            [
              4.791143511876,
              52.422941687221
            ],
            [
              4.798765218794,
              52.417432690319
            ],
            [
              4.808645209244,
              52.393494995758
            ],
            [
              4.832639471763,
              52.394011773797
            ],
            [
              4.87808742783,
              52.395389818986
            ],
            [
              4.900670263143,
              52.379539701251
            ],
            [
              4.933415374347,
              52.374542288731
            ],
            [
              4.93200394714,
              52.383330464543
            ],
            [
              4.908574255503,
              52.381607430665
            ],
            [
              4.902646261233,
              52.382468956009
            ],
            [
              4.898411979612,
              52.387465471507
            ],
            [
              4.871030291795,
              52.429138486002
            ],
            [
              4.823606337638,
              52.440497021406
            ],
            [
              4.796789220704,
              52.428794242255
            ],
            [
              4.792837224524,
              52.425351656925
            ]
          ]
        ]
      }
    },
    {
      "type": "Feature",
      "properties": {
        "name": "Centrale meldpost IJsselmeer",
        "type": "vts",
        "channel": 1,
        "phone": "+31887973300",
        "update": "15 *",
        "vhfdata": {
          "generic": {
            "mode": "listen",
            "note": "Ship to ship on VHF 10"
          },
          "cargo": {
            "mode": "report",
            "note": "Report destination."
          }
        }
      },
      "geometry": {
        "type": "Polygon",
        "coordinates": [
          [
            [
              5.377941836287,
              53.090793486449
            ],
            [
              5.340138456761,
              53.072842970909
            ],
            [
              5.339440096331,
              53.069705351598
            ],
            [
              5.341289586759,
              53.063027554387
            ],
            [
              5.33709873155,
              53.064721902772
            ],
            [
              5.333394875566,
              53.071892297095
            ],
            [
              5.299334412898,
              53.067379729697
            ],
            [
              5.284137011332,
              53.060357804206
            ],
            [
              5.045048578353,
              52.935062977618
            ],
            [
              5.055177870759,
              52.927104942656
            ],
            [
              5.050938160777,
              52.921989704247
            ],
            [
              5.079971708882,
              52.887551913336
            ],
            [
              5.116978893192,
              52.84870720621
            ],
            [
              5.10832506911,
              52.779357817886
            ],
            [
              5.115738908424,
              52.761273748089
            ],
            [
              5.153338282999,
              52.73560899781
            ],
            [
              5.16984154306,
              52.741190720171
            ],
            [
              5.194709378495,
              52.756152310598
            ],
            [
              5.258468246686,
              52.752436244226
            ],
            [
              5.286845029115,
              52.736757020213
            ],
            [
              5.286890053483,
              52.719921637159
            ],
            [
              5.302151272561,
              52.701675431652
            ],
            [
              5.269801481524,
              52.686207037918
            ],
            [
              5.24794873517,
              52.684106350291
            ],
            [
              5.233802387596,
              52.652417201119
            ],
            [
              5.134466864005,
              52.613721370997
            ],
            [
              5.120026967218,
              52.632892599154
            ],
            [
              5.0902204317,
              52.63801389811
            ],
            [
              5.064799413194,
              52.631156107582
            ],
            [
              5.054091477888,
              52.63357158584
            ],
            [
              5.053999148625,
              52.638479816081
            ],
            [
              5.047110391188,
              52.639951133841
            ],
            [
              5.041315509981,
              52.636630024124
            ],
            [
              5.022788863309,
              52.630319250798
            ],
            [
              5.025023495564,
              52.596299321506
            ],
            [
              5.032706927572,
              52.567980673562
            ],
            [
              5.087407691236,
              52.503773363121
            ],
            [
              5.079927992757,
              52.491798011354
            ],
            [
              5.060579771875,
              52.486678174725
            ],
            [
              5.050194410224,
              52.440688826704
            ],
            [
              5.08795916276,
              52.437274211063
            ],
            [
              5.067615124058,
              52.412612635657
            ],
            [
              5.055540150693,
              52.413922923051
            ],
            [
              5.029632385451,
              52.395332144951
            ],
            [
              5.014086385551,
              52.376611527978
            ],
            [
              5.01912831544,
              52.356553853602
            ],
            [
              5.045764232777,
              52.334982853745
            ],
            [
              5.079771932963,
              52.339953384302
            ],
            [
              5.093704874566,
              52.33906087945
            ],
            [
              5.112831156711,
              52.330558601284
            ],
            [
              5.123732590119,
              52.330021314172
            ],
            [
              5.129769806654,
              52.325765848796
            ],
            [
              5.14353698201,
              52.332573620087
            ],
            [
              5.134416113742,
              52.337691164204
            ],
            [
              5.131666401978,
              52.336750647271
            ],
            [
              5.127846718507,
              52.337604489354
            ],
            [
              5.133363800538,
              52.349154574213
            ],
            [
              5.130704086306,
              52.350711981287
            ],
            [
              5.131813763709,
              52.364776684589
            ],
            [
              5.119724544509,
              52.37683352595
            ],
            [
              5.122564310779,
              52.38299152053
            ],
            [
              5.263632146699,
              52.436289535889
            ],
            [
              5.388457153419,
              52.493946516802
            ],
            [
              5.420619003107,
              52.510808579791
            ],
            [
              5.432484759508,
              52.547194708394
            ],
            [
              5.49609152911,
              52.554650396617
            ],
            [
              5.555465911523,
              52.592883622661
            ],
            [
              5.629111214742,
              52.606033316015
            ],
            [
              5.649929745172,
              52.616631757648
            ],
            [
              5.616656398077,
              52.648682729969
            ],
            [
              5.590014068304,
              52.662864739827
            ],
            [
              5.591118662973,
              52.765636430536
            ],
            [
              5.660966308379,
              52.832640776136
            ],
            [
              5.678979535396,
              52.832751952183
            ],
            [
              5.665976461586,
              52.843475867634
            ],
            [
              5.657256649572,
              52.843461566359
            ],
            [
              5.656292696497,
              52.854173013568
            ],
            [
              5.642151481901,
              52.859909358116
            ],
            [
              5.619038078858,
              52.849544991873
            ],
            [
              5.601894062587,
              52.851723818394
            ],
            [
              5.585433749485,
              52.847837678936
            ],
            [
              5.580935118232,
              52.836943450325
            ],
            [
              5.546251185224,
              52.830885298917
            ],
            [
              5.461016651327,
              52.852571122429
            ],
            [
              5.418640626179,
              52.845596832463
            ],
            [
              5.376372605502,
              52.869531542086
            ],
            [
              5.358983733151,
              52.873831269962
            ],
            [
              5.350861707479,
              52.88733567897
            ],
            [
              5.370175749196,
              52.899291464747
            ],
            [
              5.39045853736,
              52.906094846694
            ],
            [
              5.393770958059,
              52.905569042884
            ],
            [
              5.401273592947,
              52.90671734199
            ],
            [
              5.406262099322,
              52.911403612864
            ],
            [
              5.409759706,
              52.921205658835
            ],
            [
              5.395339879278,
              52.943311144132
            ],
            [
              5.407578620064,
              52.949192189583
            ],
            [
              5.402846993385,
              52.959681297835
            ],
            [
              5.408468511106,
              52.966902082475
            ],
            [
              5.395439863339,
              53.003188935696
            ],
            [
              5.405421176207,
              53.016098583103
            ],
            [
              5.387062478764,
              53.040084018642
            ],
            [
              5.363557401126,
              53.063868244234
            ],
            [
              5.363314525587,
              53.075818933935
            ],
            [
              5.389776739086,
              53.074406159617
            ],
            [
              5.377941836287,
              53.090793486449
            ]
          ]
        ]
      }
    },
    {
      "type": "Feature",
      "properties": {
        "name": "IJmuiden Port Control",
        "callname": "Haven IJmuiden",
        "type": "vts",
        "channel": 61,
        "url": "https://www.binnenvaartkennis.nl/wp-content/uploads/2021/02/VTS-Amsterdam.pdf",
        "vhfdata": {
          "generic": {
            "mode": "listen"
          },
          "cargo": {
            "mode": "report",
            "note": "Report destination."
          }
        }
      },
      "geometry": {
        "type": "Polygon",
        "coordinates": [
          [
            [
              4.547817598337,
              52.459318738518
            ],
            [
              4.555779048459,
              52.461950730374
            ],
            [
              4.563566123466,
              52.462651561976
            ],
            [
              4.575904012824,
              52.462841722575
            ],
            [
              4.582572749314,
              52.463416049474
            ],
            [
              4.584203619525,
              52.465065603645
            ],
            [
              4.587187165864,
              52.467662957287
            ],
            [
              4.59080870675,
              52.470170455132
            ],
            [
              4.598199138302,
              52.472562757427
            ],
            [
              4.609448800349,
              52.471690510321
            ],
            [
              4.610990312349,
              52.473217229782
            ],
            [
              4.599313592174,
              52.47424268842
            ],
            [
              4.561345788701,
              52.467954691055
            ],
            [
              4.582447976207,
              52.49970625307
            ],
            [
              4.559102982879,
              52.507833678072
            ],
            [
              4.528992214354,
              52.510259704161
            ],
            [
              4.502816936161,
              52.506354028929
            ],
            [
              4.475890633094,
              52.494153629257
            ],
            [
              4.461715214054,
              52.476882806333
            ],
            [
              4.459714163508,
              52.458839977461
            ],
            [
              4.470724219112,
              52.440000889186
            ],
            [
              4.488186918841,
              52.428504090981
            ],
            [
              4.51345628226,
              52.420814314796
            ],
            [
              4.545617989927,
              52.415777413159
            ],
            [
              4.552789036076,
              52.424894420535
            ],
            [
              4.555769658799,
              52.445145075035
            ],
            [
              4.547817598337,
              52.459318738518
            ]
          ]
        ]
      }
    },
    {
      "type": "Feature",
      "properties": {
        "name": "Seaport IJmuiden",
        "type": "marina",
        "channel": 74,
        "url": "https://www.marinaseaport.nl/",
        "phone": "+31255560300",
        "vhfdata": {
          "generic": {
            "mode": "listen"
          }
        }
      },
      "geometry": {
        "type": "Polygon",
        "coordinates": [
          [
            [
              4.556432578421,
              52.461757838784
            ],
            [
              4.559178875051,
              52.456707092139
            ],
            [
              4.564901409155,
              52.457745981429
            ],
            [
              4.564188962202,
              52.462389092434
            ],
            [
              4.556432578421,
              52.461757838784
            ]
          ]
        ]
      }
    },
    {
      "type": "Feature",
      "properties": {
        "name": "Traffic Control Noordzeekanaal",
        "callname": "Verkeersdienst Noordzeekanaal",
        "type": "vts",
        "channel": 3,
        "url": "https://www.binnenvaartkennis.nl/wp-content/uploads/2021/02/VTS-Amsterdam.pdf",
        "phone": "+31206221515",
        "vhfdata": {
          "generic": {
            "mode": "listen"
          },
          "cargo": {
            "mode": "report",
            "note": "Report destination."
          }
        }
      },
      "geometry": {
        "type": "Polygon",
        "coordinates": [
          [
            [
              4.621761543016,
              52.469822666779
            ],
            [
              4.618122269392,
              52.462674908723
            ],
            [
              4.657045487242,
              52.459150275225
            ],
            [
              4.715949887722,
              52.430449794406
            ],
            [
              4.741025224704,
              52.426718761911
            ],
            [
              4.748544216343,
              52.410682111579
            ],
            [
              4.792434523413,
              52.398323437511
            ],
            [
              4.791454038261,
              52.426782981693
            ],
            [
              4.717801269122,
              52.437901713391
            ],
            [
              4.665766087342,
              52.463828330429
            ],
            [
              4.621761543016,
              52.469822666779
            ]
          ]
        ]
      }
    },
    {
      "type": "Feature",
      "properties": {
        "name": "Zeesluis IJmuiden",
        "type": "lock",
        "channel": 22,
        "phone": "+31255514457",
        "vhfdata": {
          "generic": {
            "mode": "announce"
          }
        }
      },
      "geometry": {
        "type": "Polygon",
        "coordinates": [
          [
            [
              4.605895388613,
              52.467908740649
            ],
            [
              4.605730570178,
              52.467442270617
            ],
            [
              4.606112704583,
              52.467358994051
            ],
            [
              4.605974301414,
              52.466476665608
            ],
            [
              4.596939558019,
              52.466443384615
            ],
            [
              4.597051236296,
              52.465312454219
            ],
            [
              4.590587267151,
              52.465046528842
            ],
            [
              4.590484434353,
              52.463883892215
            ],
            [
              4.592365459438,
              52.463883892215
            ],
            [
              4.59230869052,
              52.464382008267
            ],
            [
              4.596942792376,
              52.465013292878
            ],
            [
              4.600788461942,
              52.4656948393
            ],
            [
              4.600760992639,
              52.46614390284
            ],
            [
              4.605837414456,
              52.466276995371
            ],
            [
              4.613256194871,
              52.465412193502
            ],
            [
              4.613336715759,
              52.465179483159
            ],
            [
              4.614318941884,
              52.465212724355
            ],
            [
              4.614327244804,
              52.466559872678
            ],
            [
              4.611653309679,
              52.466792887334
            ],
            [
              4.611738967473,
              52.467558868831
            ],
            [
              4.605895388613,
              52.467908740649
            ]
          ]
        ]
      }
    },
    {
      "type": "Feature",
      "properties": {
        "name": "Lorentzsluizen",
        "type": "lock",
        "channel": 18,
        "url": "https://waterkaart.net/gids/sluis.php?naam=Lorentzsluizen",
        "phone": "+31887974589",
        "vhfdata": {
          "generic": {
            "mode": "report"
          },
          "pleasure": {
            "note": "During peak traffic (7-9h and 16-18h), only operation for commericial vessel. Pleasure crafts can join."
          }
        }
      },
      "geometry": {
        "type": "Polygon",
        "coordinates": [
          [
            [
              5.334623158861,
              53.074174055857
            ],
            [
              5.334806205875,
              53.073599131577
            ],
            [
              5.334550423044,
              53.073382047566
            ],
            [
              5.334511440009,
              53.072122945946
            ],
            [
              5.335384727592,
              53.069935086795
            ],
            [
              5.336524154501,
              53.069955293822
            ],
            [
              5.337153203431,
              53.068477495548
            ],
            [
              5.337411954796,
              53.068525745878
            ],
            [
              5.337403444303,
              53.069144419461
            ],
            [
              5.337522131701,
              53.06917184769
            ],
            [
              5.337175199309,
              53.06997548703
            ],
            [
              5.337695111332,
              53.070107930668
            ],
            [
              5.336269454605,
              53.073318689311
            ],
            [
              5.335367730493,
              53.073721759005
            ],
            [
              5.335202457352,
              53.074250094177
            ],
            [
              5.334623158861,
              53.074174055857
            ]
          ]
        ]
      }
    },
    {
      "type": "Feature",
      "properties": {
        "name": "Gemeentehaven Enkhuizen",
        "callname": "Havendienst Enkhuizen",
        "type": "marina",
        "channel": 12,
        "url": "https://www.enkhuizen.nl/direct-regelen/ontspanning-en-vrije-tijd/havens/havens-2/",
        "phone": "+31623700390",
        "vhfdata": {
          "generic": {
            "mode": "announce"
          }
        }
      },
      "geometry": {
        "type": "Polygon",
        "coordinates": [
          [
            [
              5.286296721051,
              52.695408516964
            ],
            [
              5.297343382622,
              52.701479756579
            ],
            [
              5.296726414822,
              52.703972103114
            ],
            [
              5.295374961544,
              52.706535511063
            ],
            [
              5.294669855486,
              52.706428705404
            ],
            [
              5.295698135154,
              52.704648572614
            ],
            [
              5.294846132,
              52.700927860599
            ],
            [
              5.293641575819,
              52.70103467972
            ],
            [
              5.29234888138,
              52.702067251083
            ],
            [
              5.290204183788,
              52.702227475484
            ],
            [
              5.28632610047,
              52.702334291425
            ],
            [
              5.285856029765,
              52.70139074157
            ],
            [
              5.286678653499,
              52.701479756579
            ],
            [
              5.287089965366,
              52.702013842818
            ],
            [
              5.291673154741,
              52.701426347595
            ],
            [
              5.2929952286,
              52.700732024864
            ],
            [
              5.293053987437,
              52.700162315911
            ],
            [
              5.289352180634,
              52.700821041216
            ],
            [
              5.288940868768,
              52.700055494655
            ],
            [
              5.289234662958,
              52.697936819058
            ],
            [
              5.285444717898,
              52.695978287964
            ],
            [
              5.286296721051,
              52.695408516964
            ]
          ]
        ]
      }
    },
    {
      "type": "Feature",
      "properties": {
        "name": "Port of Harlingen",
        "callname": "Havendienst Harlingen",
        "type": "marina",
        "channel": 11,
        "url": "http://",
        "phone": "+",
        "vhfdata": {
          "generic": {
            "mode": "report,announce,listen"
          },
          "pleasure": {
            "mode": "report,announce,listen"
          },
          "cargo": {
            "mode": "report,announce,listen"
          }
        }
      },
      "geometry": {
        "type": "Polygon",
        "coordinates": [
          [
            [
              5.415744781494,
              53.169234789925
            ],
            [
              5.411624908447,
              53.16967212548
            ],
            [
              5.407161712646,
              53.172810520453
            ],
            [
              5.40415763855,
              53.173530775436
            ],
            [
              5.402870178223,
              53.175871520628
            ],
            [
              5.405316352844,
              53.176720330738
            ],
            [
              5.408191680908,
              53.175511414296
            ],
            [
              5.411496162415,
              53.178263578819
            ],
            [
              5.412740707397,
              53.182352917738
            ],
            [
              5.422697067261,
              53.18500177827
            ],
            [
              5.434498786926,
              53.195595584474
            ],
            [
              5.439820289612,
              53.193872983521
            ],
            [
              5.435872077942,
              53.189090474791
            ],
            [
              5.426602363586,
              53.183793095214
            ],
            [
              5.420293807983,
              53.182147174151
            ],
            [
              5.419392585754,
              53.1792666603
            ],
            [
              5.419821739197,
              53.178469341035
            ],
            [
              5.422053337097,
              53.175665745951
            ],
            [
              5.421710014343,
              53.174045235879
            ],
            [
              5.419692993164,
              53.173427882608
            ],
            [
              5.418577194214,
              53.171369974212
            ],
            [
              5.415744781494,
              53.169234789925
            ]
          ]
        ]
      }
    }
  ]
}
